fastapi_core_database/__init__.py
fastapi_core_database/config.py
fastapi_core_database/database.py
fastapi_core_database/init_db.py
fastapi_core_database/repository.py
fastapi_core_database/security.py
rodrigo0000_fastapi_core_database-1.0.0.dist-info/METADATA
rodrigo0000_fastapi_core_database-1.0.0.dist-info/WHEEL
rodrigo0000_fastapi_core_database-1.0.0.dist-info/top_level.txt
rodrigo0000_fastapi_core_database-1.0.0.dist-info/RECORD
